aumbry/__init__.py
aumbry/cli/__init__.py
aumbry/cli/app.py
aumbry/cli/edit.py
aumbry/cli/upload.py
aumbry/cli/utils.py
aumbry/cli/view.py
aumbry/contract.py
aumbry/errors.py
aumbry/formats/__init__.py
aumbry/formats/generic.py
aumbry/formats/js.py
aumbry/formats/yml.py
aumbry/loader.py
aumbry/sources/__init__.py
aumbry/sources/consul.py
aumbry/sources/etcd2.py
aumbry/sources/fernet_file.py
aumbry/sources/local_file.py
aumbry/sources/param_store.py
aumbry/utils/__init__.py
aumbry/utils/data.py
aumbry/utils/file.py
aumbry-0.11.0.dist-info/LICENSE
aumbry-0.11.0.dist-info/METADATA
aumbry-0.11.0.dist-info/WHEEL
aumbry-0.11.0.dist-info/entry_points.txt
aumbry-0.11.0.dist-info/RECORD
