Metadata-Version: 2.1
Name: aumbry
Version: 0.11.0
Summary: Multi-type configuration library for Python
Home-page: https://github.com/pyarmory/aumbry
License: Apache v2
Keywords: configuration,yaml,etcd,json,parameter,store,multiple
Author: John Vrbanac
Author-email: john.vrbanac@linux.com
Requires-Python: >=3.7,<4.0
Classifier: Development Status :: 3 - Alpha
Classifier: Intended Audience :: Developers
Classifier: License :: OSI Approved :: Apache Software License
Classifier: License :: Other/Proprietary License
Classifier: Programming Language :: Python :: 3
Classifier: Programming Language :: Python :: 3.7
Classifier: Programming Language :: Python :: 3.8
Classifier: Programming Language :: Python :: 3.9
Classifier: Programming Language :: Python :: 3.10
Classifier: Programming Language :: Python :: 3.11
Classifier: Programming Language :: Python :: 3.12
Provides-Extra: cli
Provides-Extra: consul
Provides-Extra: etcd2
Provides-Extra: fernet
Provides-Extra: param-store
Provides-Extra: yaml
Requires-Dist: alchemize (>=0.11.0)
Requires-Dist: cryptography (>=2.1.2) ; extra == "fernet" or extra == "cli"
Requires-Dist: deepmerge
Requires-Dist: pike (>=0.2.0)
Requires-Dist: pyyaml (>=5.1) ; extra == "yaml" or extra == "cli"
